ctyunsdk_monitor20220909/__init__.py
ctyunsdk_monitor20220909/client.py
ctyunsdk_monitor20220909/monitor_client.py
ctyunsdk_monitor20220909/models/__init__.py
ctyunsdk_monitor20220909/models/lcm_test003.py
ctyunsdk_monitor20220909/models/v41_monitor_change_alarm_rules_status.py
ctyunsdk_monitor20220909/models/v41_monitor_create_alarm_rule.py
ctyunsdk_monitor20220909/models/v41_monitor_delete_alarm_rules.py
ctyunsdk_monitor20220909/models/v41_monitor_describe_alarm_rule.py
ctyunsdk_monitor20220909/models/v41_monitor_query_alarm_rules.py
ctyunsdk_monitor20220909/models/v41_monitor_query_contact_groups.py
ctyunsdk_monitor20220909/models/v41_monitor_query_contacts.py
ctyunsdk_monitor20220909/models/v41_monitor_task_center_query_task.py
ctyunsdk_monitor20220909/models/v41_monitor_update_alarm_rule.py
ctyunsdk_monitor20220909/models/v4_monitor_activate_contact.py
ctyunsdk_monitor20220909/models/v4_monitor_alarm_rule_query_binding_notice_strategy.py
ctyunsdk_monitor20220909/models/v4_monitor_canvas_query_history_data.py
ctyunsdk_monitor20220909/models/v4_monitor_canvas_query_region_deploy.py
ctyunsdk_monitor20220909/models/v4_monitor_canvas_query_resource_child.py
ctyunsdk_monitor20220909/models/v4_monitor_canvas_query_resource_detail.py
ctyunsdk_monitor20220909/models/v4_monitor_canvas_query_resource_list.py
ctyunsdk_monitor20220909/models/v4_monitor_canvas_query_view_data.py
ctyunsdk_monitor20220909/models/v4_monitor_contact_activation_code.py
ctyunsdk_monitor20220909/models/v4_monitor_create_contact.py
ctyunsdk_monitor20220909/models/v4_monitor_create_contact_group.py
ctyunsdk_monitor20220909/models/v4_monitor_create_event_alarm_rule.py
ctyunsdk_monitor20220909/models/v4_monitor_create_site_monitor.py
ctyunsdk_monitor20220909/models/v4_monitor_delete_alarm_rules.py
ctyunsdk_monitor20220909/models/v4_monitor_delete_contact.py
ctyunsdk_monitor20220909/models/v4_monitor_delete_contact_group.py
ctyunsdk_monitor20220909/models/v4_monitor_delete_contact_groups.py
ctyunsdk_monitor20220909-0.0.5.13.dist-info/licenses/LICENSE.txt
ctyunsdk_monitor20220909-0.0.5.13.dist-info/METADATA
ctyunsdk_monitor20220909-0.0.5.13.dist-info/WHEEL
ctyunsdk_monitor20220909-0.0.5.13.dist-info/top_level.txt
ctyunsdk_monitor20220909-0.0.5.13.dist-info/RECORD
